<?xml version="1.0" encoding="UTF-8" standalone="no"?>
<scene depth="1" desc="" eventsnippetid="18" extheight="1184" extwidth="1024" extx="-32" exty="-32" format="3.4.0" gravx="-0.0" gravy="80.0" height="1120" id="2" name="Level 3" revision="" savecount="0" tiled="1" tileh="32" tilew="32" type="standard" width="960">
    <layers>
        <color-bg blue="204" green="255" red="204"/>
        <layer blendMode="normal" color="100,168,234" id="0" locked="false" name="Layer 0" opacity="100" order="0" scrollFactorX="1.0" scrollFactorY="1.0" visible="true"/>
    </layers>
    <joints/>
    <regions>
        <region b="64" g="64" h="99" id="0" name="Region 0" pts="4,85.0,0.0,85.0,99.0,0.0,99.0,0.0,0.0" r="64" type="box" w="85" x="438" y="987"/>
    </regions>
    <terrainRegions>
        <terrainRegion b="64" g="64" group="1" h="95" id="0" name="Terrain 0" pts="4,85.0,0.0,85.0,95.0,0.0,95.0,0.0,0.0" r="64" type="box" w="85" x="448" y="989"/>
    </terrainRegions>
    <actors>
        <actor a="0.0" aid="1" c="false" group="4" id="5" name="Cannibal 1" sx="1.0" sy="1.0" x="671" y="127" z="0"/>
        <actor a="0.0" aid="3" c="false" group="0" id="3" name="Mark 3" sx="1.0" sy="1.0" x="16" y="30" z="0"/>
        <actor a="0.0" aid="4" c="false" group="5" id="7" name="munEz 4" sx="1.0" sy="1.0" x="431" y="155" z="0"/>
        <actor a="0.0" aid="5" c="false" group="5" id="7" name="munEz 5" sx="1.0" sy="1.0" x="607" y="122" z="0"/>
        <actor a="0.0" aid="6" c="false" group="5" id="7" name="munEz 6" sx="1.0" sy="1.0" x="753" y="119" z="0"/>
        <actor a="0.0" aid="7" c="false" group="5" id="7" name="munEz 7" sx="1.0" sy="1.0" x="898" y="254" z="0"/>
        <actor a="0.0" aid="8" c="false" group="5" id="7" name="munEz 8" sx="1.0" sy="1.0" x="773" y="689" z="0"/>
        <actor a="0.0" aid="9" c="false" group="5" id="7" name="munEz 9" sx="1.0" sy="1.0" x="687" y="763" z="0"/>
        <actor a="0.0" aid="10" c="false" group="5" id="7" name="munEz 10" sx="1.0" sy="1.0" x="615" y="851" z="0"/>
        <actor a="0.0" aid="11" c="false" group="5" id="7" name="munEz 11" sx="1.0" sy="1.0" x="393" y="1047" z="0"/>
        <actor a="0.0" aid="12" c="false" group="5" id="7" name="munEz 12" sx="1.0" sy="1.0" x="834" y="205" z="0"/>
        <actor a="0.0" aid="13" c="false" group="5" id="7" name="munEz 13" sx="1.0" sy="1.0" x="569" y="954" z="0"/>
        <actor a="0.0" aid="14" c="false" group="4" id="5" name="Cannibal 14" sx="1.0" sy="1.0" x="640" y="543" z="0"/>
        <actor a="0.0" aid="15" c="false" group="5" id="7" name="munEz 15" sx="1.0" sy="1.0" x="269" y="121" z="0"/>
        <actor a="0.0" aid="16" c="false" group="5" id="7" name="munEz 16" sx="1.0" sy="1.0" x="397" y="413" z="0"/>
    </actors>
    <snippets>
        <s enabled="true" id="26"/>
        <s enabled="true" id="12">
            <prop id="1" list="0" val="0"/>
            <prop id="2" list="0" val="3"/>
            <prop id="4" list="0" val="3"/>
            <prop id="7" list="0" val="false"/>
            <prop id="8" list="0" val="false"/>
            <prop id="9" list="0" val="No Control"/>
            <prop id="10" list="0" val="1"/>
            <prop id="11" list="0" val="1"/>
            <prop id="12" list="0" val="Blur"/>
        </s>
    </snippets>
    <terrain>
        <p pts="4,32.0,0.0,32.0,32.0,0.0,32.0,0.0,0.0" x="160.0" y="288.0"/>
        <p pts="4,32.0,0.0,32.0,32.0,0.0,32.0,0.0,0.0" x="160.0" y="352.0"/>
        <p pts="3,32.0,32.0,0.0,32.0,32.0,0.0" x="256.0" y="576.0"/>
        <p pts="3,32.0,32.0,0.0,32.0,32.0,0.0" x="352.0" y="480.0"/>
        <p pts="3,32.0,32.0,0.0,32.0,0.0,0.0" x="448.0" y="480.0"/>
        <p pts="3,32.0,32.0,0.0,32.0,0.0,0.0" x="544.0" y="576.0"/>
        <p pts="3,32.0,32.0,0.0,32.0,32.0,0.0" x="288.0" y="544.0"/>
        <p pts="3,32.0,32.0,0.0,32.0,0.0,0.0" x="512.0" y="544.0"/>
        <p pts="3,32.0,32.0,0.0,32.0,32.0,0.0" x="320.0" y="512.0"/>
        <p pts="3,32.0,32.0,0.0,32.0,0.0,0.0" x="480.0" y="512.0"/>
        <p pts="4,0.0,32.0,0.0,0.0,64.0,0.0,64.0,32.0" x="640.0" y="608.0"/>
        <p pts="4,96.0,0.0,96.0,32.0,0.0,32.0,0.0,0.0" x="864.0" y="576.0"/>
        <p pts="4,0.0,32.0,0.0,0.0,64.0,0.0,64.0,32.0" x="96.0" y="384.0"/>
        <p pts="4,0.0,32.0,0.0,0.0,64.0,0.0,64.0,32.0" x="96.0" y="320.0"/>
        <p pts="4,0.0,32.0,0.0,0.0,64.0,0.0,64.0,32.0" x="736.0" y="160.0"/>
        <p pts="4,64.0,0.0,64.0,32.0,0.0,32.0,0.0,0.0" x="96.0" y="256.0"/>
        <p pts="3,32.0,0.0,64.0,32.0,0.0,32.0" x="384.0" y="448.0"/>
        <p pts="5,64.0,32.0,64.0,64.0,0.0,64.0,0.0,32.0,32.0,0.0" x="416.0" y="192.0"/>
        <p pts="5,0.0,32.0,32.0,0.0,64.0,32.0,64.0,64.0,0.0,64.0" x="256.0" y="160.0"/>
        <p pts="4,0.0,32.0,0.0,0.0,128.0,0.0,128.0,32.0" x="416.0" y="1088.0"/>
        <p pts="9,64.0,0.0,96.0,32.0,160.0,32.0,160.0,64.0,96.0,64.0,96.0,96.0,0.0,96.0,0.0,32.0,32.0,0.0" x="576.0" y="160.0"/>
        <p pts="4,0.0,64.0,0.0,0.0,192.0,0.0,192.0,64.0" x="0.0" y="96.0"/>
    </terrain>
    <atlases members="0,1,2,3," retainAtlases="false"/>
</scene>
